{
  "model_name": "surus-factura",
  "publisher": "unknown",
  "full_model_name": "surus-factura",
  "categories": {
    "image_extraction": {
      "model_name": "surus-factura",
      "task_scores": {
        "extraction_quality_score": {
          "score": 0.9749285714285714,
          "stderr": 0.0,
          "metric": "eqs",
          "alias": "extraction_quality_score"
        },
        "composite_score": {
          "score": 0.9830943844754401,
          "stderr": 0.1027568456963134,
          "metric": "composite_mean",
          "alias": "composite_score"
        },
        "schema_validity": {
          "score": 1.0,
          "stderr": 0.0,
          "metric": "validity_rate",
          "alias": "schema_validity"
        },
        "field_f1_partial": {
          "score": 0.9582142857142857,
          "stderr": 0.0,
          "metric": "f1",
          "alias": "field_f1_partial"
        },
        "hallucination_rate": {
          "score": 0.0,
          "stderr": 0.0,
          "metric": "hallucination_rate",
          "alias": "hallucination_rate"
        }
      },
      "category_scores": {
        "image_extraction": {
          "score": 0.9749285714285714,
          "stderr": 0.0,
          "metric": "eqs",
          "alias": "image_extraction"
        }
      },
      "top_level_scores": {
        "image_extraction": {
          "score": 0.9749285714285714,
          "stderr": 0.0,
          "metric": "eqs",
          "alias": "image_extraction"
        }
      },
      "overall_score": 0.9749285714285714,
      "evaluation_time": "20251226_153718"
    }
  },
  "overall_latam_score": null
}